{
   "EXPLORE":{
        "1":{
          "ExploreId":"9",
          "Probability":"10",
          "Assemble":"1001,2000|1002,2000|1003,2000|1004,2000|1005,2000",
          "DefaultEvent":"9"
        },
        "2":{
          "ExploreId":"10",
          "Probability":"10",
          "Assemble":"1001,2000|1002,2000|1003,2000|1004,2000|1005,2000",
          "DefaultEvent":"10"
        },
        "3":{
          "ExploreId":"11",
          "Probability":"10",
          "Assemble":"1001,2000|1002,2000|1003,2000|1004,2000|1005,2000",
          "DefaultEvent":"11"
        },
        "4":{
          "ExploreId":"12",
          "Probability":"10",
          "Assemble":"1001,2000|1002,2000|1003,2000|1004,2000|1005,2000",
          "DefaultEvent":"12"
        },
        "5":{
          "ExploreId":"13",
          "Probability":"10",
          "Assemble":"1001,2000|1002,2000|1003,2000|1004,2000|1005,2000",
          "DefaultEvent":"13"
        },
        "6":{
          "ExploreId":"14",
          "Probability":"10",
          "Assemble":"1001,2000|1002,2000|1003,2000|1004,2000|1005,2000",
          "DefaultEvent":"14"
        },
        "7":{
          "ExploreId":"15",
          "Probability":"10",
          "Assemble":"1001,2000|1002,2000|1003,2000|1004,2000|1005,2000",
          "DefaultEvent":"15"
        },
        "8":{
          "ExploreId":"16",
          "Probability":"10",
          "Assemble":"1001,2000|1002,2000|1003,2000|1004,2000|1005,2000",
          "DefaultEvent":"16"
        },
        "9":{
          "ExploreId":"17",
          "Probability":"10",
          "Assemble":"1001,2000|1002,2000|1003,2000|1004,2000|1005,2000",
          "DefaultEvent":"17"
        },
        "10":{
          "ExploreId":"18",
          "Probability":"10",
          "Assemble":"1001,2000|1002,2000|1003,2000|1004,2000|1005,2000",
          "DefaultEvent":"18"
        },
        "11":{
          "ExploreId":"19",
          "Probability":"10",
          "Assemble":"1001,2000|1002,2000|1003,2000|1004,2000|1005,2000",
          "DefaultEvent":"19"
        },
        "12":{
          "ExploreId":"20",
          "Probability":"10",
          "Assemble":"1001,2000|1002,2000|1003,2000|1004,2000|1005,2000",
          "DefaultEvent":"20"
        },
        "13":{
          "ExploreId":"21",
          "Probability":"10",
          "Assemble":"1001,2000|1002,2000|1003,2000|1004,2000|1005,2000",
          "DefaultEvent":"21"
        },
        "14":{
          "ExploreId":"22",
          "Probability":"10",
          "Assemble":"2001,961|2002,961|2003,961|2004,961|2005,961|2006,961|2007,961|2008,961|2009,961|2010,961|2011,78|2012,78|2013,78|2014,78|2015,78",
          "DefaultEvent":"22"
        },
        "15":{
          "ExploreId":"23",
          "Probability":"10",
          "Assemble":"2001,961|2002,961|2003,961|2004,961|2005,961|2006,961|2007,961|2008,961|2009,961|2010,961|2011,78|2012,78|2013,78|2014,78|2015,78",
          "DefaultEvent":"23"
        },
        "16":{
          "ExploreId":"24",
          "Probability":"10",
          "Assemble":"2001,961|2002,961|2003,961|2004,961|2005,961|2006,961|2007,961|2008,961|2009,961|2010,961|2011,78|2012,78|2013,78|2014,78|2015,78",
          "DefaultEvent":"24"
        },
        "17":{
          "ExploreId":"25",
          "Probability":"10",
          "Assemble":"2001,961|2002,961|2003,961|2004,961|2005,961|2006,961|2007,961|2008,961|2009,961|2010,961|2011,78|2012,78|2013,78|2014,78|2015,78",
          "DefaultEvent":"25"
        },
        "18":{
          "ExploreId":"26",
          "Probability":"10",
          "Assemble":"2001,961|2002,961|2003,961|2004,961|2005,961|2006,961|2007,961|2008,961|2009,961|2010,961|2011,78|2012,78|2013,78|2014,78|2015,78",
          "DefaultEvent":"26"
        },
        "19":{
          "ExploreId":"27",
          "Probability":"10",
          "Assemble":"2001,961|2002,961|2003,961|2004,961|2005,961|2006,961|2007,961|2008,961|2009,961|2010,961|2011,78|2012,78|2013,78|2014,78|2015,78",
          "DefaultEvent":"27"
        },
        "20":{
          "ExploreId":"28",
          "Probability":"10",
          "Assemble":"2001,961|2002,961|2003,961|2004,961|2005,961|2006,961|2007,961|2008,961|2009,961|2010,961|2011,78|2012,78|2013,78|2014,78|2015,78",
          "DefaultEvent":"28"
        },
        "21":{
          "ExploreId":"29",
          "Probability":"10",
          "Assemble":"2001,961|2002,961|2003,961|2004,961|2005,961|2006,961|2007,961|2008,961|2009,961|2010,961|2011,78|2012,78|2013,78|2014,78|2015,78",
          "DefaultEvent":"29"
        },
        "22":{
          "ExploreId":"30",
          "Probability":"10",
          "Assemble":"2001,961|2002,961|2003,961|2004,961|2005,961|2006,961|2007,961|2008,961|2009,961|2010,961|2011,78|2012,78|2013,78|2014,78|2015,78",
          "DefaultEvent":"30"
        },
        "23":{
          "ExploreId":"31",
          "Probability":"10",
          "Assemble":"2001,961|2002,961|2003,961|2004,961|2005,961|2006,961|2007,961|2008,961|2009,961|2010,961|2011,78|2012,78|2013,78|2014,78|2015,78",
          "DefaultEvent":"31"
        },
        "24":{
          "ExploreId":"32",
          "Probability":"10",
          "Assemble":"3001,19|3002,19|3003,19|3004,19|3005,19|3006,19|3007,19|3008,19|3009,19|3010,19|3011,1682|3012,1682|3013,1682|3014,1682|3015,1682|3016,280|3017,280|3018,280|3019,280|3020,280",
          "DefaultEvent":"32"
        },
        "25":{
          "ExploreId":"33",
          "Probability":"10",
          "Assemble":"3001,19|3002,19|3003,19|3004,19|3005,19|3006,19|3007,19|3008,19|3009,19|3010,19|3011,1682|3012,1682|3013,1682|3014,1682|3015,1682|3016,280|3017,280|3018,280|3019,280|3020,280",
          "DefaultEvent":"33"
        },
        "26":{
          "ExploreId":"34",
          "Probability":"10",
          "Assemble":"3001,19|3002,19|3003,19|3004,19|3005,19|3006,19|3007,19|3008,19|3009,19|3010,19|3011,1682|3012,1682|3013,1682|3014,1682|3015,1682|3016,280|3017,280|3018,280|3019,280|3020,280",
          "DefaultEvent":"34"
        },
        "27":{
          "ExploreId":"35",
          "Probability":"10",
          "Assemble":"3001,19|3002,19|3003,19|3004,19|3005,19|3006,19|3007,19|3008,19|3009,19|3010,19|3011,1682|3012,1682|3013,1682|3014,1682|3015,1682|3016,280|3017,280|3018,280|3019,280|3020,280",
          "DefaultEvent":"35"
        },
        "28":{
          "ExploreId":"36",
          "Probability":"10",
          "Assemble":"3001,19|3002,19|3003,19|3004,19|3005,19|3006,19|3007,19|3008,19|3009,19|3010,19|3011,1682|3012,1682|3013,1682|3014,1682|3015,1682|3016,280|3017,280|3018,280|3019,280|3020,280",
          "DefaultEvent":"36"
        },
        "29":{
          "ExploreId":"37",
          "Probability":"10",
          "Assemble":"3001,19|3002,19|3003,19|3004,19|3005,19|3006,19|3007,19|3008,19|3009,19|3010,19|3011,1682|3012,1682|3013,1682|3014,1682|3015,1682|3016,280|3017,280|3018,280|3019,280|3020,280",
          "DefaultEvent":"37"
        },
        "30":{
          "ExploreId":"38",
          "Probability":"10",
          "Assemble":"3001,19|3002,19|3003,19|3004,19|3005,19|3006,19|3007,19|3008,19|3009,19|3010,19|3011,1682|3012,1682|3013,1682|3014,1682|3015,1682|3016,280|3017,280|3018,280|3019,280|3020,280",
          "DefaultEvent":"38"
        },
        "31":{
          "ExploreId":"39",
          "Probability":"10",
          "Assemble":"3001,19|3002,19|3003,19|3004,19|3005,19|3006,19|3007,19|3008,19|3009,19|3010,19|3011,1682|3012,1682|3013,1682|3014,1682|3015,1682|3016,280|3017,280|3018,280|3019,280|3020,280",
          "DefaultEvent":"39"
        },
        "32":{
          "ExploreId":"40",
          "Probability":"10",
          "Assemble":"4001,677|4002,674|4003,674|4004,674|4005,674|4006,1123|4007,1123|4008,1123|4009,1123|4010,1123|4011,135|4012,135|4013,135|4014,135|4015,135|4016,337",
          "DefaultEvent":"40"
        },
        "33":{
          "ExploreId":"41",
          "Probability":"10",
          "Assemble":"4001,677|4002,674|4003,674|4004,674|4005,674|4006,1123|4007,1123|4008,1123|4009,1123|4010,1123|4011,135|4012,135|4013,135|4014,135|4015,135|4016,337",
          "DefaultEvent":"41"
        },
        "34":{
          "ExploreId":"42",
          "Probability":"10",
          "Assemble":"4001,677|4002,674|4003,674|4004,674|4005,674|4006,1123|4007,1123|4008,1123|4009,1123|4010,1123|4011,135|4012,135|4013,135|4014,135|4015,135|4016,337",
          "DefaultEvent":"42"
        },
        "35":{
          "ExploreId":"43",
          "Probability":"10",
          "Assemble":"4001,677|4002,674|4003,674|4004,674|4005,674|4006,1123|4007,1123|4008,1123|4009,1123|4010,1123|4011,135|4012,135|4013,135|4014,135|4015,135|4016,337",
          "DefaultEvent":"43"
        },
        "36":{
          "ExploreId":"44",
          "Probability":"10",
          "Assemble":"4001,677|4002,674|4003,674|4004,674|4005,674|4006,1123|4007,1123|4008,1123|4009,1123|4010,1123|4011,135|4012,135|4013,135|4014,135|4015,135|4016,337",
          "DefaultEvent":"44"
        },
        "37":{
          "ExploreId":"45",
          "Probability":"10",
          "Assemble":"5001,1481|5002,1475|5003,1475|5004,1475|5005,1475|5006,327|5007,327|5008,327|5009,327|5010,327|5011,148|5012,148|5013,148|5014,148|5015,148|5016,39|5017,39|5018,39|5019,39|5020,39|5021,49",
          "DefaultEvent":"45"
        },
        "38":{
          "ExploreId":"46",
          "Probability":"10",
          "Assemble":"5001,1481|5002,1475|5003,1475|5004,1475|5005,1475|5006,327|5007,327|5008,327|5009,327|5010,327|5011,148|5012,148|5013,148|5014,148|5015,148|5016,39|5017,39|5018,39|5019,39|5020,39|5021,49",
          "DefaultEvent":"46"
        },
        "39":{
          "ExploreId":"47",
          "Probability":"10",
          "Assemble":"5001,1481|5002,1475|5003,1475|5004,1475|5005,1475|5006,327|5007,327|5008,327|5009,327|5010,327|5011,148|5012,148|5013,148|5014,148|5015,148|5016,39|5017,39|5018,39|5019,39|5020,39|5021,49",
          "DefaultEvent":"47"
        },
        "40":{
          "ExploreId":"48",
          "Probability":"10",
          "Assemble":"5001,1481|5002,1475|5003,1475|5004,1475|5005,1475|5006,327|5007,327|5008,327|5009,327|5010,327|5011,148|5012,148|5013,148|5014,148|5015,148|5016,39|5017,39|5018,39|5019,39|5020,39|5021,49",
          "DefaultEvent":"48"
        },
        "41":{
          "ExploreId":"49",
          "Probability":"10",
          "Assemble":"5001,1481|5002,1475|5003,1475|5004,1475|5005,1475|5006,327|5007,327|5008,327|5009,327|5010,327|5011,148|5012,148|5013,148|5014,148|5015,148|5016,39|5017,39|5018,39|5019,39|5020,39|5021,49",
          "DefaultEvent":"49"
        },
        "42":{
          "ExploreId":"50",
          "Probability":"10",
          "Assemble":"5001,1481|5002,1475|5003,1475|5004,1475|5005,1475|5006,327|5007,327|5008,327|5009,327|5010,327|5011,148|5012,148|5013,148|5014,148|5015,148|5016,39|5017,39|5018,39|5019,39|5020,39|5021,49",
          "DefaultEvent":"50"
        },
        "43":{
          "ExploreId":"51",
          "Probability":"10",
          "Assemble":"5001,1481|5002,1475|5003,1475|5004,1475|5005,1475|5006,327|5007,327|5008,327|5009,327|5010,327|5011,148|5012,148|5013,148|5014,148|5015,148|5016,39|5017,39|5018,39|5019,39|5020,39|5021,49",
          "DefaultEvent":"51"
        },
        "44":{
          "ExploreId":"52",
          "Probability":"10",
          "Assemble":"5001,1481|5002,1475|5003,1475|5004,1475|5005,1475|5006,327|5007,327|5008,327|5009,327|5010,327|5011,148|5012,148|5013,148|5014,148|5015,148|5016,39|5017,39|5018,39|5019,39|5020,39|5021,49",
          "DefaultEvent":"52"
        },
        "45":{
          "ExploreId":"53",
          "Probability":"10",
          "Assemble":"5001,1481|5002,1475|5003,1475|5004,1475|5005,1475|5006,327|5007,327|5008,327|5009,327|5010,327|5011,148|5012,148|5013,148|5014,148|5015,148|5016,39|5017,39|5018,39|5019,39|5020,39|5021,49",
          "DefaultEvent":"53"
        },
        "46":{
          "ExploreId":"54",
          "Probability":"10",
          "Assemble":"5001,1481|5002,1475|5003,1475|5004,1475|5005,1475|5006,327|5007,327|5008,327|5009,327|5010,327|5011,148|5012,148|5013,148|5014,148|5015,148|5016,39|5017,39|5018,39|5019,39|5020,39|5021,49",
          "DefaultEvent":"54"
        },
        "47":{
          "ExploreId":"55",
          "Probability":"10",
          "Assemble":"5001,1481|5002,1475|5003,1475|5004,1475|5005,1475|5006,327|5007,327|5008,327|5009,327|5010,327|5011,148|5012,148|5013,148|5014,148|5015,148|5016,39|5017,39|5018,39|5019,39|5020,39|5021,49",
          "DefaultEvent":"55"
        },
        "48":{
          "ExploreId":"56",
          "Probability":"10",
          "Assemble":"5001,1481|5002,1475|5003,1475|5004,1475|5005,1475|5006,327|5007,327|5008,327|5009,327|5010,327|5011,148|5012,148|5013,148|5014,148|5015,148|5016,39|5017,39|5018,39|5019,39|5020,39|5021,49",
          "DefaultEvent":"56"
        },
        "49":{
          "ExploreId":"57",
          "Probability":"10",
          "Assemble":"5001,1481|5002,1475|5003,1475|5004,1475|5005,1475|5006,327|5007,327|5008,327|5009,327|5010,327|5011,148|5012,148|5013,148|5014,148|5015,148|5016,39|5017,39|5018,39|5019,39|5020,39|5021,49",
          "DefaultEvent":"57"
        },
        "50":{
          "ExploreId":"58",
          "Probability":"10",
          "Assemble":"5001,1481|5002,1475|5003,1475|5004,1475|5005,1475|5006,327|5007,327|5008,327|5009,327|5010,327|5011,148|5012,148|5013,148|5014,148|5015,148|5016,39|5017,39|5018,39|5019,39|5020,39|5021,49",
          "DefaultEvent":"58"
        },
        "51":{
          "ExploreId":"59",
          "Probability":"10",
          "Assemble":"5001,1481|5002,1475|5003,1475|5004,1475|5005,1475|5006,327|5007,327|5008,327|5009,327|5010,327|5011,148|5012,148|5013,148|5014,148|5015,148|5016,39|5017,39|5018,39|5019,39|5020,39|5021,49",
          "DefaultEvent":"59"
        },
        "52":{
          "ExploreId":"60",
          "Probability":"10",
          "Assemble":"5001,1481|5002,1475|5003,1475|5004,1475|5005,1475|5006,327|5007,327|5008,327|5009,327|5010,327|5011,148|5012,148|5013,148|5014,148|5015,148|5016,39|5017,39|5018,39|5019,39|5020,39|5021,49",
          "DefaultEvent":"60"
        },
        "53":{
          "ExploreId":"61",
          "Probability":"10",
          "Assemble":"5001,1481|5002,1475|5003,1475|5004,1475|5005,1475|5006,327|5007,327|5008,327|5009,327|5010,327|5011,148|5012,148|5013,148|5014,148|5015,148|5016,39|5017,39|5018,39|5019,39|5020,39|5021,49",
          "DefaultEvent":"61"
        },
        "54":{
          "ExploreId":"62",
          "Probability":"10",
          "Assemble":"6001,1481|6002,1475|6003,1475|6004,1475|6005,1475|6006,327|6007,327|6008,327|6009,327|6010,327|6011,148|6012,148|6013,148|6014,148|6015,148|6016,39|6017,39|6018,39|6019,39|6020,39|6021,49",
          "DefaultEvent":"62"
        },
        "55":{
          "ExploreId":"63",
          "Probability":"10",
          "Assemble":"6001,1481|6002,1475|6003,1475|6004,1475|6005,1475|6006,327|6007,327|6008,327|6009,327|6010,327|6011,148|6012,148|6013,148|6014,148|6015,148|6016,39|6017,39|6018,39|6019,39|6020,39|6021,49",
          "DefaultEvent":"63"
        },
        "56":{
          "ExploreId":"64",
          "Probability":"10",
          "Assemble":"6001,1481|6002,1475|6003,1475|6004,1475|6005,1475|6006,327|6007,327|6008,327|6009,327|6010,327|6011,148|6012,148|6013,148|6014,148|6015,148|6016,39|6017,39|6018,39|6019,39|6020,39|6021,49",
          "DefaultEvent":"64"
        },
        "57":{
          "ExploreId":"65",
          "Probability":"10",
          "Assemble":"6001,1481|6002,1475|6003,1475|6004,1475|6005,1475|6006,327|6007,327|6008,327|6009,327|6010,327|6011,148|6012,148|6013,148|6014,148|6015,148|6016,39|6017,39|6018,39|6019,39|6020,39|6021,49",
          "DefaultEvent":"65"
        },
        "58":{
          "ExploreId":"66",
          "Probability":"10",
          "Assemble":"6001,1481|6002,1475|6003,1475|6004,1475|6005,1475|6006,327|6007,327|6008,327|6009,327|6010,327|6011,148|6012,148|6013,148|6014,148|6015,148|6016,39|6017,39|6018,39|6019,39|6020,39|6021,49",
          "DefaultEvent":"66"
        },
        "59":{
          "ExploreId":"67",
          "Probability":"10",
          "Assemble":"6001,1481|6002,1475|6003,1475|6004,1475|6005,1475|6006,327|6007,327|6008,327|6009,327|6010,327|6011,148|6012,148|6013,148|6014,148|6015,148|6016,39|6017,39|6018,39|6019,39|6020,39|6021,49",
          "DefaultEvent":"67"
        },
        "60":{
          "ExploreId":"68",
          "Probability":"10",
          "Assemble":"6001,1481|6002,1475|6003,1475|6004,1475|6005,1475|6006,327|6007,327|6008,327|6009,327|6010,327|6011,148|6012,148|6013,148|6014,148|6015,148|6016,39|6017,39|6018,39|6019,39|6020,39|6021,49",
          "DefaultEvent":"68"
        },
        "61":{
          "ExploreId":"69",
          "Probability":"10",
          "Assemble":"6001,1481|6002,1475|6003,1475|6004,1475|6005,1475|6006,327|6007,327|6008,327|6009,327|6010,327|6011,148|6012,148|6013,148|6014,148|6015,148|6016,39|6017,39|6018,39|6019,39|6020,39|6021,49",
          "DefaultEvent":"69"
        },
        "62":{
          "ExploreId":"70",
          "Probability":"10",
          "Assemble":"6001,1481|6002,1475|6003,1475|6004,1475|6005,1475|6006,327|6007,327|6008,327|6009,327|6010,327|6011,148|6012,148|6013,148|6014,148|6015,148|6016,39|6017,39|6018,39|6019,39|6020,39|6021,49",
          "DefaultEvent":"70"
        },
        "63":{
          "ExploreId":"71",
          "Probability":"10",
          "Assemble":"6001,1481|6002,1475|6003,1475|6004,1475|6005,1475|6006,327|6007,327|6008,327|6009,327|6010,327|6011,148|6012,148|6013,148|6014,148|6015,148|6016,39|6017,39|6018,39|6019,39|6020,39|6021,49",
          "DefaultEvent":"71"
        },
        "64":{
          "ExploreId":"72",
          "Probability":"10",
          "Assemble":"6001,1481|6002,1475|6003,1475|6004,1475|6005,1475|6006,327|6007,327|6008,327|6009,327|6010,327|6011,148|6012,148|6013,148|6014,148|6015,148|6016,39|6017,39|6018,39|6019,39|6020,39|6021,49",
          "DefaultEvent":"72"
        },
        "65":{
          "ExploreId":"73",
          "Probability":"10",
          "Assemble":"6001,1481|6002,1475|6003,1475|6004,1475|6005,1475|6006,327|6007,327|6008,327|6009,327|6010,327|6011,148|6012,148|6013,148|6014,148|6015,148|6016,39|6017,39|6018,39|6019,39|6020,39|6021,49",
          "DefaultEvent":"73"
        },
        "66":{
          "ExploreId":"74",
          "Probability":"10",
          "Assemble":"6001,1481|6002,1475|6003,1475|6004,1475|6005,1475|6006,327|6007,327|6008,327|6009,327|6010,327|6011,148|6012,148|6013,148|6014,148|6015,148|6016,39|6017,39|6018,39|6019,39|6020,39|6021,49",
          "DefaultEvent":"74"
        },
        "67":{
          "ExploreId":"75",
          "Probability":"10",
          "Assemble":"6001,1481|6002,1475|6003,1475|6004,1475|6005,1475|6006,327|6007,327|6008,327|6009,327|6010,327|6011,148|6012,148|6013,148|6014,148|6015,148|6016,39|6017,39|6018,39|6019,39|6020,39|6021,49",
          "DefaultEvent":"75"
        },
        "68":{
          "ExploreId":"76",
          "Probability":"10",
          "Assemble":"6001,1481|6002,1475|6003,1475|6004,1475|6005,1475|6006,327|6007,327|6008,327|6009,327|6010,327|6011,148|6012,148|6013,148|6014,148|6015,148|6016,39|6017,39|6018,39|6019,39|6020,39|6021,49",
          "DefaultEvent":"76"
        },
        "69":{
          "ExploreId":"77",
          "Probability":"10",
          "Assemble":"6001,1481|6002,1475|6003,1475|6004,1475|6005,1475|6006,327|6007,327|6008,327|6009,327|6010,327|6011,148|6012,148|6013,148|6014,148|6015,148|6016,39|6017,39|6018,39|6019,39|6020,39|6021,49",
          "DefaultEvent":"77"
        },
        "70":{
          "ExploreId":"78",
          "Probability":"10",
          "Assemble":"6001,1481|6002,1475|6003,1475|6004,1475|6005,1475|6006,327|6007,327|6008,327|6009,327|6010,327|6011,148|6012,148|6013,148|6014,148|6015,148|6016,39|6017,39|6018,39|6019,39|6020,39|6021,49",
          "DefaultEvent":"78"
        },
        "71":{
          "ExploreId":"79",
          "Probability":"10",
          "Assemble":"6001,1481|6002,1475|6003,1475|6004,1475|6005,1475|6006,327|6007,327|6008,327|6009,327|6010,327|6011,148|6012,148|6013,148|6014,148|6015,148|6016,39|6017,39|6018,39|6019,39|6020,39|6021,49",
          "DefaultEvent":"79"
        },
        "72":{
          "ExploreId":"80",
          "Probability":"10",
          "Assemble":"6001,1481|6002,1475|6003,1475|6004,1475|6005,1475|6006,327|6007,327|6008,327|6009,327|6010,327|6011,148|6012,148|6013,148|6014,148|6015,148|6016,39|6017,39|6018,39|6019,39|6020,39|6021,49",
          "DefaultEvent":"80"
        },
        "73":{
          "ExploreId":"81",
          "Probability":"10",
          "Assemble":"7001,1078|7002,1071|7003,1071|7004,1071|7005,1071|7006,714|7007,714|7008,714|7009,714|7010,714|7011,160|7012,160|7013,160|7014,160|7015,160|7016,43|7017,43|7018,43|7019,43|7020,43|7021,53",
          "DefaultEvent":"81"
        },
        "74":{
          "ExploreId":"82",
          "Probability":"10",
          "Assemble":"7001,1078|7002,1071|7003,1071|7004,1071|7005,1071|7006,714|7007,714|7008,714|7009,714|7010,714|7011,160|7012,160|7013,160|7014,160|7015,160|7016,43|7017,43|7018,43|7019,43|7020,43|7021,53",
          "DefaultEvent":"82"
        },
        "75":{
          "ExploreId":"83",
          "Probability":"10",
          "Assemble":"7001,1078|7002,1071|7003,1071|7004,1071|7005,1071|7006,714|7007,714|7008,714|7009,714|7010,714|7011,160|7012,160|7013,160|7014,160|7015,160|7016,43|7017,43|7018,43|7019,43|7020,43|7021,53",
          "DefaultEvent":"83"
        },
        "76":{
          "ExploreId":"84",
          "Probability":"10",
          "Assemble":"7001,1078|7002,1071|7003,1071|7004,1071|7005,1071|7006,714|7007,714|7008,714|7009,714|7010,714|7011,160|7012,160|7013,160|7014,160|7015,160|7016,43|7017,43|7018,43|7019,43|7020,43|7021,53",
          "DefaultEvent":"84"
        },
        "77":{
          "ExploreId":"85",
          "Probability":"10",
          "Assemble":"7001,1078|7002,1071|7003,1071|7004,1071|7005,1071|7006,714|7007,714|7008,714|7009,714|7010,714|7011,160|7012,160|7013,160|7014,160|7015,160|7016,43|7017,43|7018,43|7019,43|7020,43|7021,53",
          "DefaultEvent":"85"
        },
        "78":{
          "ExploreId":"86",
          "Probability":"10",
          "Assemble":"7001,1078|7002,1071|7003,1071|7004,1071|7005,1071|7006,714|7007,714|7008,714|7009,714|7010,714|7011,160|7012,160|7013,160|7014,160|7015,160|7016,43|7017,43|7018,43|7019,43|7020,43|7021,53",
          "DefaultEvent":"86"
        },
        "79":{
          "ExploreId":"87",
          "Probability":"10",
          "Assemble":"7001,1078|7002,1071|7003,1071|7004,1071|7005,1071|7006,714|7007,714|7008,714|7009,714|7010,714|7011,160|7012,160|7013,160|7014,160|7015,160|7016,43|7017,43|7018,43|7019,43|7020,43|7021,53",
          "DefaultEvent":"87"
        },
        "80":{
          "ExploreId":"88",
          "Probability":"10",
          "Assemble":"7001,1078|7002,1071|7003,1071|7004,1071|7005,1071|7006,714|7007,714|7008,714|7009,714|7010,714|7011,160|7012,160|7013,160|7014,160|7015,160|7016,43|7017,43|7018,43|7019,43|7020,43|7021,53",
          "DefaultEvent":"88"
        },
        "81":{
          "ExploreId":"89",
          "Probability":"10",
          "Assemble":"7001,1078|7002,1071|7003,1071|7004,1071|7005,1071|7006,714|7007,714|7008,714|7009,714|7010,714|7011,160|7012,160|7013,160|7014,160|7015,160|7016,43|7017,43|7018,43|7019,43|7020,43|7021,53",
          "DefaultEvent":"89"
        },
        "82":{
          "ExploreId":"90",
          "Probability":"10",
          "Assemble":"7001,1078|7002,1071|7003,1071|7004,1071|7005,1071|7006,714|7007,714|7008,714|7009,714|7010,714|7011,160|7012,160|7013,160|7014,160|7015,160|7016,43|7017,43|7018,43|7019,43|7020,43|7021,53",
          "DefaultEvent":"90"
        },
        "83":{
          "ExploreId":"91",
          "Probability":"10",
          "Assemble":"7001,1078|7002,1071|7003,1071|7004,1071|7005,1071|7006,714|7007,714|7008,714|7009,714|7010,714|7011,160|7012,160|7013,160|7014,160|7015,160|7016,43|7017,43|7018,43|7019,43|7020,43|7021,53",
          "DefaultEvent":"91"
        },
        "84":{
          "ExploreId":"92",
          "Probability":"10",
          "Assemble":"7001,1078|7002,1071|7003,1071|7004,1071|7005,1071|7006,714|7007,714|7008,714|7009,714|7010,714|7011,160|7012,160|7013,160|7014,160|7015,160|7016,43|7017,43|7018,43|7019,43|7020,43|7021,53",
          "DefaultEvent":"92"
        },
        "85":{
          "ExploreId":"93",
          "Probability":"10",
          "Assemble":"7001,1078|7002,1071|7003,1071|7004,1071|7005,1071|7006,714|7007,714|7008,714|7009,714|7010,714|7011,160|7012,160|7013,160|7014,160|7015,160|7016,43|7017,43|7018,43|7019,43|7020,43|7021,53",
          "DefaultEvent":"93"
        },
        "86":{
          "ExploreId":"94",
          "Probability":"10",
          "Assemble":"7001,1078|7002,1071|7003,1071|7004,1071|7005,1071|7006,714|7007,714|7008,714|7009,714|7010,714|7011,160|7012,160|7013,160|7014,160|7015,160|7016,43|7017,43|7018,43|7019,43|7020,43|7021,53",
          "DefaultEvent":"94"
        },
        "87":{
          "ExploreId":"95",
          "Probability":"10",
          "Assemble":"7001,1078|7002,1071|7003,1071|7004,1071|7005,1071|7006,714|7007,714|7008,714|7009,714|7010,714|7011,160|7012,160|7013,160|7014,160|7015,160|7016,43|7017,43|7018,43|7019,43|7020,43|7021,53",
          "DefaultEvent":"95"
        },
        "88":{
          "ExploreId":"96",
          "Probability":"10",
          "Assemble":"7001,1078|7002,1071|7003,1071|7004,1071|7005,1071|7006,714|7007,714|7008,714|7009,714|7010,714|7011,160|7012,160|7013,160|7014,160|7015,160|7016,43|7017,43|7018,43|7019,43|7020,43|7021,53",
          "DefaultEvent":"96"
        },
        "89":{
          "ExploreId":"97",
          "Probability":"10",
          "Assemble":"7001,1078|7002,1071|7003,1071|7004,1071|7005,1071|7006,714|7007,714|7008,714|7009,714|7010,714|7011,160|7012,160|7013,160|7014,160|7015,160|7016,43|7017,43|7018,43|7019,43|7020,43|7021,53",
          "DefaultEvent":"97"
        },
        "90":{
          "ExploreId":"98",
          "Probability":"10",
          "Assemble":"7001,1078|7002,1071|7003,1071|7004,1071|7005,1071|7006,714|7007,714|7008,714|7009,714|7010,714|7011,160|7012,160|7013,160|7014,160|7015,160|7016,43|7017,43|7018,43|7019,43|7020,43|7021,53",
          "DefaultEvent":"98"
        },
        "91":{
          "ExploreId":"99",
          "Probability":"10",
          "Assemble":"7001,1078|7002,1071|7003,1071|7004,1071|7005,1071|7006,714|7007,714|7008,714|7009,714|7010,714|7011,160|7012,160|7013,160|7014,160|7015,160|7016,43|7017,43|7018,43|7019,43|7020,43|7021,53",
          "DefaultEvent":"99"
        },
        "92":{
          "ExploreId":"100",
          "Probability":"10",
          "Assemble":"7001,1078|7002,1071|7003,1071|7004,1071|7005,1071|7006,714|7007,714|7008,714|7009,714|7010,714|7011,160|7012,160|7013,160|7014,160|7015,160|7016,43|7017,43|7018,43|7019,43|7020,43|7021,53",
          "DefaultEvent":"100"
        }
   }
}
