{
   "PLAY_FIRST_NAME":{
        "1":{
          "FirstName":"赵"
        },
        "2":{
          "FirstName":"钱"
        },
        "3":{
          "FirstName":"孙"
        },
        "4":{
          "FirstName":"周"
        },
        "5":{
          "FirstName":"吴"
        },
        "6":{
          "FirstName":"郑"
        },
        "7":{
          "FirstName":"冯"
        },
        "8":{
          "FirstName":"陈"
        },
        "9":{
          "FirstName":"卫"
        },
        "10":{
          "FirstName":"蒋"
        },
        "11":{
          "FirstName":"沈"
        },
        "12":{
          "FirstName":"韩"
        },
        "13":{
          "FirstName":"杨"
        },
        "14":{
          "FirstName":"朱"
        },
        "15":{
          "FirstName":"秦"
        },
        "16":{
          "FirstName":"许"
        },
        "17":{
          "FirstName":"何"
        },
        "18":{
          "FirstName":"吕"
        },
        "19":{
          "FirstName":"施"
        },
        "20":{
          "FirstName":"张"
        },
        "21":{
          "FirstName":"孔"
        },
        "22":{
          "FirstName":"曹"
        },
        "23":{
          "FirstName":"严"
        },
        "24":{
          "FirstName":"华"
        },
        "25":{
          "FirstName":"魏"
        },
        "26":{
          "FirstName":"陶"
        },
        "27":{
          "FirstName":"姜"
        },
        "28":{
          "FirstName":"戚"
        },
        "29":{
          "FirstName":"谢"
        },
        "30":{
          "FirstName":"柏"
        },
        "31":{
          "FirstName":"水"
        },
        "32":{
          "FirstName":"章"
        },
        "33":{
          "FirstName":"云"
        },
        "34":{
          "FirstName":"苏"
        },
        "35":{
          "FirstName":"潘"
        },
        "36":{
          "FirstName":"葛"
        },
        "37":{
          "FirstName":"奚"
        },
        "38":{
          "FirstName":"范"
        },
        "39":{
          "FirstName":"彭"
        },
        "40":{
          "FirstName":"鲁"
        },
        "41":{
          "FirstName":"韦"
        },
        "42":{
          "FirstName":"昌"
        },
        "43":{
          "FirstName":"马"
        },
        "44":{
          "FirstName":"苗"
        },
        "45":{
          "FirstName":"凤"
        },
        "46":{
          "FirstName":"花"
        },
        "47":{
          "FirstName":"方"
        },
        "48":{
          "FirstName":"俞"
        },
        "49":{
          "FirstName":"任"
        },
        "50":{
          "FirstName":"袁"
        },
        "51":{
          "FirstName":"柳"
        },
        "52":{
          "FirstName":"史"
        },
        "53":{
          "FirstName":"唐"
        },
        "54":{
          "FirstName":"岑"
        },
        "55":{
          "FirstName":"薛"
        },
        "56":{
          "FirstName":"雷"
        },
        "57":{
          "FirstName":"贺"
        },
        "58":{
          "FirstName":"倪"
        },
        "59":{
          "FirstName":"汤"
        },
        "60":{
          "FirstName":"殷"
        },
        "61":{
          "FirstName":"罗"
        },
        "62":{
          "FirstName":"毕"
        },
        "63":{
          "FirstName":"常"
        },
        "64":{
          "FirstName":"乐"
        },
        "65":{
          "FirstName":"于"
        },
        "66":{
          "FirstName":"时"
        },
        "67":{
          "FirstName":"傅"
        },
        "68":{
          "FirstName":"卞"
        },
        "69":{
          "FirstName":"齐"
        },
        "70":{
          "FirstName":"康"
        },
        "71":{
          "FirstName":"余"
        },
        "72":{
          "FirstName":"元"
        },
        "73":{
          "FirstName":"卜"
        },
        "74":{
          "FirstName":"顾"
        },
        "75":{
          "FirstName":"孟"
        },
        "76":{
          "FirstName":"平"
        },
        "77":{
          "FirstName":"黄"
        },
        "78":{
          "FirstName":"和"
        },
        "79":{
          "FirstName":"穆"
        },
        "80":{
          "FirstName":"萧"
        },
        "81":{
          "FirstName":"尹"
        },
        "82":{
          "FirstName":"姚"
        },
        "83":{
          "FirstName":"邵"
        },
        "84":{
          "FirstName":"汪"
        },
        "85":{
          "FirstName":"毛"
        },
        "86":{
          "FirstName":"明"
        },
        "87":{
          "FirstName":"计"
        },
        "88":{
          "FirstName":"伏"
        },
        "89":{
          "FirstName":"成"
        },
        "90":{
          "FirstName":"戴"
        },
        "91":{
          "FirstName":"纪"
        },
        "92":{
          "FirstName":"舒"
        },
        "93":{
          "FirstName":"屈"
        },
        "94":{
          "FirstName":"项"
        },
        "95":{
          "FirstName":"祝"
        },
        "96":{
          "FirstName":"董"
        },
        "97":{
          "FirstName":"梁"
        },
        "98":{
          "FirstName":"杜"
        },
        "99":{
          "FirstName":"阮"
        },
        "100":{
          "FirstName":"蓝"
        },
        "101":{
          "FirstName":"童"
        },
        "102":{
          "FirstName":"颜"
        },
        "103":{
          "FirstName":"梅"
        },
        "104":{
          "FirstName":"徐"
        },
        "105":{
          "FirstName":"骆"
        },
        "106":{
          "FirstName":"夏"
        },
        "107":{
          "FirstName":"蔡"
        },
        "108":{
          "FirstName":"田"
        },
        "109":{
          "FirstName":"凌"
        },
        "110":{
          "FirstName":"万"
        },
        "111":{
          "FirstName":"卢"
        },
        "112":{
          "FirstName":"宗"
        },
        "113":{
          "FirstName":"邓"
        },
        "114":{
          "FirstName":"杭"
        },
        "115":{
          "FirstName":"包"
        },
        "116":{
          "FirstName":"左"
        },
        "117":{
          "FirstName":"石"
        },
        "118":{
          "FirstName":"崔"
        },
        "119":{
          "FirstName":"程"
        },
        "120":{
          "FirstName":"陆"
        },
        "121":{
          "FirstName":"荣"
        },
        "122":{
          "FirstName":"甄"
        },
        "123":{
          "FirstName":"曲"
        },
        "124":{
          "FirstName":"封"
        },
        "125":{
          "FirstName":"段"
        },
        "126":{
          "FirstName":"巫"
        },
        "127":{
          "FirstName":"乌"
        },
        "128":{
          "FirstName":"秋"
        },
        "129":{
          "FirstName":"仲"
        },
        "130":{
          "FirstName":"伊"
        },
        "131":{
          "FirstName":"宫"
        },
        "132":{
          "FirstName":"宁"
        },
        "133":{
          "FirstName":"武"
        },
        "134":{
          "FirstName":"符"
        },
        "135":{
          "FirstName":"刘"
        },
        "136":{
          "FirstName":"景"
        },
        "137":{
          "FirstName":"龙"
        },
        "138":{
          "FirstName":"叶"
        },
        "139":{
          "FirstName":"司"
        },
        "140":{
          "FirstName":"苍"
        },
        "141":{
          "FirstName":"双"
        },
        "142":{
          "FirstName":"姬"
        },
        "143":{
          "FirstName":"桑"
        },
        "144":{
          "FirstName":"牛"
        },
        "145":{
          "FirstName":"燕"
        },
        "146":{
          "FirstName":"尚"
        },
        "147":{
          "FirstName":"庄"
        },
        "148":{
          "FirstName":"晏"
        },
        "149":{
          "FirstName":"古"
        },
        "150":{
          "FirstName":"文"
        },
        "151":{
          "FirstName":"广"
        },
        "152":{
          "FirstName":"师"
        },
        "153":{
          "FirstName":"丰"
        },
        "154":{
          "FirstName":"关"
        },
        "155":{
          "FirstName":"欧阳"
        },
        "156":{
          "FirstName":"太史"
        },
        "157":{
          "FirstName":"端木"
        },
        "158":{
          "FirstName":"上官"
        },
        "159":{
          "FirstName":"司马"
        },
        "160":{
          "FirstName":"东方"
        },
        "161":{
          "FirstName":"南宫"
        },
        "162":{
          "FirstName":"万俟"
        },
        "163":{
          "FirstName":"夏侯"
        },
        "164":{
          "FirstName":"诸葛"
        },
        "165":{
          "FirstName":"尉迟"
        },
        "166":{
          "FirstName":"公羊"
        },
        "167":{
          "FirstName":"赫连"
        },
        "168":{
          "FirstName":"澹台"
        },
        "169":{
          "FirstName":"皇甫"
        },
        "170":{
          "FirstName":"宗政"
        },
        "171":{
          "FirstName":"濮阳"
        },
        "172":{
          "FirstName":"公冶"
        },
        "173":{
          "FirstName":"太叔"
        },
        "174":{
          "FirstName":"申屠"
        },
        "175":{
          "FirstName":"公孙"
        },
        "176":{
          "FirstName":"慕容"
        },
        "177":{
          "FirstName":"仲孙"
        },
        "178":{
          "FirstName":"钟离"
        },
        "179":{
          "FirstName":"长孙"
        },
        "180":{
          "FirstName":"宇文"
        },
        "181":{
          "FirstName":"司徒"
        },
        "182":{
          "FirstName":"鲜于"
        },
        "183":{
          "FirstName":"司空"
        },
        "184":{
          "FirstName":"闾丘"
        },
        "185":{
          "FirstName":"子车"
        },
        "186":{
          "FirstName":"亓官"
        },
        "187":{
          "FirstName":"司寇"
        },
        "188":{
          "FirstName":"巫马"
        },
        "189":{
          "FirstName":"公良"
        },
        "190":{
          "FirstName":"漆雕"
        },
        "191":{
          "FirstName":"乐正"
        },
        "192":{
          "FirstName":"宰父"
        },
        "193":{
          "FirstName":"谷梁"
        },
        "194":{
          "FirstName":"拓跋"
        },
        "195":{
          "FirstName":"夹谷"
        },
        "196":{
          "FirstName":"轩辕"
        },
        "197":{
          "FirstName":"令狐"
        },
        "198":{
          "FirstName":"百里"
        },
        "199":{
          "FirstName":"呼延"
        },
        "200":{
          "FirstName":"南门"
        },
        "201":{
          "FirstName":"羊舌"
        },
        "202":{
          "FirstName":"微生"
        },
        "203":{
          "FirstName":"公仪"
        },
        "204":{
          "FirstName":"梁丘"
        },
        "205":{
          "FirstName":"公仲"
        },
        "206":{
          "FirstName":"公门"
        },
        "207":{
          "FirstName":"公坚"
        },
        "208":{
          "FirstName":"左丘"
        },
        "209":{
          "FirstName":"公伯"
        },
        "210":{
          "FirstName":"西门"
        },
        "211":{
          "FirstName":"公祖"
        },
        "212":{
          "FirstName":"第五"
        },
        "213":{
          "FirstName":"公乘"
        },
        "214":{
          "FirstName":"贯丘"
        },
        "215":{
          "FirstName":"南荣"
        },
        "216":{
          "FirstName":"东里"
        },
        "217":{
          "FirstName":"东宫"
        },
        "218":{
          "FirstName":"仲长"
        },
        "219":{
          "FirstName":"子书"
        },
        "220":{
          "FirstName":"子桑"
        },
        "221":{
          "FirstName":"士季"
        },
        "222":{
          "FirstName":"士孙"
        },
        "223":{
          "FirstName":"叔孙"
        },
        "224":{
          "FirstName":"叔先"
        },
        "225":{
          "FirstName":"叔促"
        },
        "226":{
          "FirstName":"水丘"
        },
        "227":{
          "FirstName":"司城"
        },
        "228":{
          "FirstName":"西乡"
        },
        "229":{
          "FirstName":"千代"
        },
        "230":{
          "FirstName":"勤宿"
        },
        "231":{
          "FirstName":"青阳"
        },
        "232":{
          "FirstName":"丘陵"
        },
        "233":{
          "FirstName":"屈侯"
        },
        "234":{
          "FirstName":"屈男"
        },
        "235":{
          "FirstName":"屈卢"
        }
   }
}
